[
    {
    "pieceType": "Start",
    "pieceTiles": [
        {"tileType": "corn",
        "x": 0,
        "y": 0},
        {"tileType": "cocoa",
        "x": 1,
        "y": 0},
        {"tileType": "grass",
        "x": 2,
        "y": 0},
        {"tileType": "potato",
        "x": 3,
        "y": 0},
        {"tileType": "grass",
        "x": 0,
        "y": 1},
        {"tileType": "grass",
        "x": 1,
        "y": 1},
        {"tileType": "grass",
        "x": 2,
        "y": 1},
        {"tileType": "cocoa",
        "x": 3,
        "y": 1},
        {"tileType": "potato",
        "x": 0,
        "y": 2},
        {"tileType": "grass",
        "x": 1,
        "y": 2},
        {"tileType": "grass",
        "x": 2,
        "y": 2},
        {"tileType": "grass",
        "x": 3,
        "y": 2},
        {"tileType": "corn",
        "x": 0,
        "y": 3},
        {"tileType": "grass",
        "x": 1,
        "y": 3},
        {"tileType": "potato",
        "x": 2,
        "y": 3},
        {"tileType": "cocoa",
        "x": 3,
        "y": 3}
   ]
},
{
    "pieceType": "Start",
    "pieceTiles": [
    {"tileType": "potato",
    "x": 0,
    "y": 0},
    {"tileType": "cocoa",
    "x": 1,
    "y": 0},
    {"tileType": "grass",
    "x": 2,
    "y": 0},
    {"tileType": "corn",
    "x": 3,
    "y": 0},
    {"tileType": "grass",
    "x": 0,
    "y": 1},
    {"tileType": "grass",
    "x": 1,
    "y": 1},
    {"tileType": "grass",
    "x": 2,
    "y": 1},
    {"tileType": "potato",
    "x": 3,
    "y": 1},
    {"tileType": "corn",
    "x": 0,
    "y": 2},
    {"tileType": "grass",
    "x": 1,
    "y": 2},
    {"tileType": "grass",
    "x": 2,
    "y": 2},
    {"tileType": "grass",
    "x": 3,
    "y": 2},
    {"tileType": "cocoa",
    "x": 0,
    "y": 3},
    {"tileType": "grass",
    "x": 1,
    "y": 3},
    {"tileType": "corn",
    "x": 2,
    "y": 3},
    {"tileType": "cocoa",
    "x": 3,
    "y": 3}
   ]
}]